droidconfig.py
droidcountry.py
droidlysis3.py
droidproperties.py
droidreport.py
droidsample.py
droidsql.py
droidurl.py
droidutil.py
droidziprar.py
conf/__init__.py
conf/arm.conf
conf/exodustrack.py
conf/general.conf
conf/kit.conf
conf/manifest.conf
conf/smali.conf
conf/sortconf.py
conf/wide.conf
droidlysis-3.4.7.data/scripts/droidlysis
droidlysis-3.4.7.data/scripts/droidlysis3.py
droidlysis-3.4.7.dist-info/LICENSE
droidlysis-3.4.7.dist-info/METADATA
droidlysis-3.4.7.dist-info/WHEEL
droidlysis-3.4.7.dist-info/top_level.txt
droidlysis-3.4.7.dist-info/RECORD
