Metadata-Version: 2.1
Name: droidlysis
Version: 3.4.7
Summary: DroidLysis: pre-analysis of suspicious Android samples
Home-page: https://github.com/cryptax/droidlysis
Author: @cryptax
Author-email: aafortinet@gmail.com
License: MIT
Keywords: android malware reverse
Classifier: Programming Language :: Python :: 3
Classifier: License :: OSI Approved :: MIT License
Classifier: Development Status :: 3 - Alpha
Classifier: Operating System :: Unix
Classifier: Topic :: Software Development :: Disassemblers
Requires-Python: >=3.0
License-File: LICENSE
Requires-Dist: configparser >=4.0.2
Requires-Dist: python-magic ==0.4.12
Requires-Dist: requests
Requires-Dist: SQLAlchemy >=1.1.1
Requires-Dist: rarfile >=3.0
Requires-Dist: platformdirs
